orm_query_api/__init__.py
orm_query_api/registry.py
orm_query_api/routes.py
orm_query_api/exceptions/__init__.py
orm_query_api/exceptions/error.py
orm_query_api/parser/__init__.py
orm_query_api/parser/query_parse.py
orm_query_api/parser/query_parser.py
orm_query_api/parser/query_validation.py
orm_query_api/services/__init__.py
orm_query_api/services/db_services.py
orm_query_api/services/exc_handlers.py
orm_query_api/services/serialization.py
orm_query_api/utils/__init__.py
orm_query_api/utils/auto_gen.py
orm_query_api-0.1.0.dist-info/licenses/LICENSE
orm_query_api-0.1.0.dist-info/METADATA
orm_query_api-0.1.0.dist-info/WHEEL
orm_query_api-0.1.0.dist-info/top_level.txt
orm_query_api-0.1.0.dist-info/RECORD
