Metadata-Version: 2.4
Name: orm_query_api
Version: 0.1.0
Summary: Generalized RESTful ORM API for SQLAlchemy models with auto-CRUD
Author-email: kkommatt <matviigame@gmail.com>
License: MIT
Project-URL: Homepage, https://github.com/kkommatt/orm-query-api
Project-URL: Repository, https://github.com/kkommatt/orm-query-api
Keywords: fastapi,sqlalchemy,orm,crud,auto,api
Classifier: Programming Language :: Python :: 3
Classifier: Framework :: FastAPI
Classifier: License :: OSI Approved :: MIT License
Classifier: Operating System :: OS Independent
Requires-Python: >=3.9
License-File: LICENSE
Requires-Dist: annotated-types>=0.7.0
Requires-Dist: anyio<5.0.0,>=4.0.0
Requires-Dist: fastapi<1.0.0,>=0.110.0
Requires-Dist: greenlet>=3.0.0
Requires-Dist: idna>=3.0
Requires-Dist: lark>=1.1.0
Requires-Dist: pydantic<3.0.0,>=2.0.0
Requires-Dist: pydantic_core>=2.0.0
Requires-Dist: sniffio>=1.0.0
Requires-Dist: SQLAlchemy<3.0.0,>=2.0.0
Requires-Dist: SQLAlchemy-Utils>=0.41.0
Requires-Dist: starlette>=0.36.0
Requires-Dist: typing-inspection>=0.4.0
Requires-Dist: typing_extensions>=4.0.0
Dynamic: license-file
